genemapper/__init__.py
genemapper/cli.py
genemapper-1.0.4.dist-info/AUTHORS.rst
genemapper-1.0.4.dist-info/LICENSE
genemapper-1.0.4.dist-info/METADATA
genemapper-1.0.4.dist-info/WHEEL
genemapper-1.0.4.dist-info/entry_points.txt
genemapper-1.0.4.dist-info/top_level.txt
genemapper-1.0.4.dist-info/RECORD
