Metadata-Version: 2.2
Name: genemapper
Version: 1.0.4
Summary: A command-line tool for retrieving GenBank metadata and mapping coding sequences between query and subject FASTA files to identify their most similar counterparts.
Author-email: Mohammed Salim Dason <mohammed.dason@polito.it>
Maintainer-email: Mohammed Salim Dason <mohammed.dason@polito.it>
License: MIT license
Project-URL: bugs, https://github.com/salimdason/genemapper/issues
Project-URL: changelog, https://github.com/salimdason/genemapper/blob/master/changelog.md
Project-URL: homepage, https://github.com/salimdason/genemapper
License-File: LICENSE
License-File: AUTHORS.rst
Requires-Dist: biopython>=1.78
Requires-Dist: openpyxl==3.1.5
Requires-Dist: pandas>2.0
Provides-Extra: dev
Requires-Dist: coverage; extra == "dev"
Requires-Dist: mypy; extra == "dev"
Requires-Dist: pytest; extra == "dev"
Requires-Dist: ruff; extra == "dev"
